fastlapjv.cp36-win_amd64.pyd
fastlapjv-1.0.0.dist-info/DESCRIPTION.rst
fastlapjv-1.0.0.dist-info/METADATA
fastlapjv-1.0.0.dist-info/RECORD
fastlapjv-1.0.0.dist-info/WHEEL
fastlapjv-1.0.0.dist-info/metadata.json
fastlapjv-1.0.0.dist-info/top_level.txt
