Metadata-Version: 2.0
Name: fastlapjv
Version: 1.0.0
Summary: Linear sum assignment problem solver using Jonker-Volgenant algorithm.
Home-page: https://github.com/thu-vis/fast-lapjv
Author: Thuvis
Author-email: vagroup@126.com
License: MIT
Download-URL: https://github.com/thu-vis/fast-lapjv
Platform: UNKNOWN
Classifier: Development Status :: 4 - Beta
Classifier: Intended Audience :: Developers
Classifier: License :: OSI Approved :: MIT License
Classifier: Operating System :: POSIX :: Linux
Classifier: Topic :: Scientific/Engineering :: Information Analysis
Classifier: Programming Language :: Python :: 3.5
Classifier: Programming Language :: Python :: 3.6
Requires-Dist: numpy
